{
  "description": "SAM-40 balanced sample dataset (100 samples)",
  "created": "2024-12-29",
  "n_samples": 100,
  "shape": [
    100,
    32,
    512
  ],
  "n_channels": 32,
  "segment_length": 512,
  "sampling_rate": 256,
  "class_distribution": {
    "baseline": 50,
    "stress": 50
  },
  "source": "SAM-40 filtered_data",
  "samples": [
    {
      "subject": 15,
      "condition": "Arithmetic",
      "trial": 2,
      "file": "Arithmetic_sub_15_trial2"
    },
    {
      "subject": 23,
      "condition": "Arithmetic",
      "trial": 2,
      "file": "Arithmetic_sub_23_trial2"
    },
    {
      "subject": 17,
      "condition": "Relax",
      "trial": 2,
      "file": "Relax_sub_17_trial2"
    },
    {
      "subject": 23,
      "condition": "Relax",
      "trial": 2,
      "file": "Relax_sub_23_trial2"
    },
    {
      "subject": 16,
      "condition": "Relax",
      "trial": 2,
      "file": "Relax_sub_16_trial2"
    },
    {
      "subject": 1,
      "condition": "Arithmetic",
      "trial": 2,
      "file": "Arithmetic_sub_1_trial2"
    },
    {
      "subject": 16,
      "condition": "Arithmetic",
      "trial": 2,
      "file": "Arithmetic_sub_16_trial2"
    },
    {
      "subject": 19,
      "condition": "Relax",
      "trial": 1,
      "file": "Relax_sub_19_trial1"
    },
    {
      "subject": 25,
      "condition": "Relax",
      "trial": 1,
      "file": "Relax_sub_25_trial1"
    },
    {
      "subject": 25,
      "condition": "Relax",
      "trial": 2,
      "file": "Relax_sub_25_trial2"
    },
    {
      "subject": 10,
      "condition": "Relax",
      "trial": 1,
      "file": "Relax_sub_10_trial1"
    },
    {
      "subject": 15,
      "condition": "Relax",
      "trial": 1,
      "file": "Relax_sub_15_trial1"
    },
    {
      "subject": 16,
      "condition": "Arithmetic",
      "trial": 1,
      "file": "Arithmetic_sub_16_trial1"
    },
    {
      "subject": 21,
      "condition": "Arithmetic",
      "trial": 3,
      "file": "Arithmetic_sub_21_trial3"
    },
    {
      "subject": 18,
      "condition": "Relax",
      "trial": 3,
      "file": "Relax_sub_18_trial3"
    },
    {
      "subject": 12,
      "condition": "Arithmetic",
      "trial": 2,
      "file": "Arithmetic_sub_12_trial2"
    },
    {
      "subject": 21,
      "condition": "Arithmetic",
      "trial": 2,
      "file": "Arithmetic_sub_21_trial2"
    },
    {
      "subject": 24,
      "condition": "Arithmetic",
      "trial": 3,
      "file": "Arithmetic_sub_24_trial3"
    },
    {
      "subject": 19,
      "condition": "Arithmetic",
      "trial": 3,
      "file": "Arithmetic_sub_19_trial3"
    },
    {
      "subject": 23,
      "condition": "Arithmetic",
      "trial": 1,
      "file": "Arithmetic_sub_23_trial1"
    },
    {
      "subject": 11,
      "condition": "Arithmetic",
      "trial": 1,
      "file": "Arithmetic_sub_11_trial1"
    },
    {
      "subject": 22,
      "condition": "Relax",
      "trial": 1,
      "file": "Relax_sub_22_trial1"
    },
    {
      "subject": 12,
      "condition": "Relax",
      "trial": 3,
      "file": "Relax_sub_12_trial3"
    },
    {
      "subject": 19,
      "condition": "Relax",
      "trial": 2,
      "file": "Relax_sub_19_trial2"
    },
    {
      "subject": 13,
      "condition": "Relax",
      "trial": 2,
      "file": "Relax_sub_13_trial2"
    },
    {
      "subject": 18,
      "condition": "Relax",
      "trial": 1,
      "file": "Relax_sub_18_trial1"
    },
    {
      "subject": 13,
      "condition": "Arithmetic",
      "trial": 1,
      "file": "Arithmetic_sub_13_trial1"
    },
    {
      "subject": 19,
      "condition": "Arithmetic",
      "trial": 1,
      "file": "Arithmetic_sub_19_trial1"
    },
    {
      "subject": 24,
      "condition": "Arithmetic",
      "trial": 2,
      "file": "Arithmetic_sub_24_trial2"
    },
    {
      "subject": 1,
      "condition": "Arithmetic",
      "trial": 3,
      "file": "Arithmetic_sub_1_trial3"
    },
    {
      "subject": 21,
      "condition": "Relax",
      "trial": 3,
      "file": "Relax_sub_21_trial3"
    },
    {
      "subject": 21,
      "condition": "Relax",
      "trial": 1,
      "file": "Relax_sub_21_trial1"
    },
    {
      "subject": 17,
      "condition": "Relax",
      "trial": 3,
      "file": "Relax_sub_17_trial3"
    },
    {
      "subject": 19,
      "condition": "Arithmetic",
      "trial": 2,
      "file": "Arithmetic_sub_19_trial2"
    },
    {
      "subject": 24,
      "condition": "Relax",
      "trial": 1,
      "file": "Relax_sub_24_trial1"
    },
    {
      "subject": 1,
      "condition": "Relax",
      "trial": 3,
      "file": "Relax_sub_1_trial3"
    },
    {
      "subject": 22,
      "condition": "Relax",
      "trial": 3,
      "file": "Relax_sub_22_trial3"
    },
    {
      "subject": 18,
      "condition": "Arithmetic",
      "trial": 2,
      "file": "Arithmetic_sub_18_trial2"
    },
    {
      "subject": 24,
      "condition": "Relax",
      "trial": 3,
      "file": "Relax_sub_24_trial3"
    },
    {
      "subject": 19,
      "condition": "Relax",
      "trial": 3,
      "file": "Relax_sub_19_trial3"
    },
    {
      "subject": 13,
      "condition": "Arithmetic",
      "trial": 2,
      "file": "Arithmetic_sub_13_trial2"
    },
    {
      "subject": 13,
      "condition": "Arithmetic",
      "trial": 3,
      "file": "Arithmetic_sub_13_trial3"
    },
    {
      "subject": 20,
      "condition": "Arithmetic",
      "trial": 3,
      "file": "Arithmetic_sub_20_trial3"
    },
    {
      "subject": 20,
      "condition": "Relax",
      "trial": 1,
      "file": "Relax_sub_20_trial1"
    },
    {
      "subject": 18,
      "condition": "Relax",
      "trial": 2,
      "file": "Relax_sub_18_trial2"
    },
    {
      "subject": 14,
      "condition": "Arithmetic",
      "trial": 1,
      "file": "Arithmetic_sub_14_trial1"
    },
    {
      "subject": 25,
      "condition": "Arithmetic",
      "trial": 1,
      "file": "Arithmetic_sub_25_trial1"
    },
    {
      "subject": 17,
      "condition": "Arithmetic",
      "trial": 2,
      "file": "Arithmetic_sub_17_trial2"
    },
    {
      "subject": 20,
      "condition": "Arithmetic",
      "trial": 2,
      "file": "Arithmetic_sub_20_trial2"
    },
    {
      "subject": 23,
      "condition": "Arithmetic",
      "trial": 3,
      "file": "Arithmetic_sub_23_trial3"
    },
    {
      "subject": 22,
      "condition": "Arithmetic",
      "trial": 1,
      "file": "Arithmetic_sub_22_trial1"
    },
    {
      "subject": 17,
      "condition": "Relax",
      "trial": 1,
      "file": "Relax_sub_17_trial1"
    },
    {
      "subject": 24,
      "condition": "Arithmetic",
      "trial": 1,
      "file": "Arithmetic_sub_24_trial1"
    },
    {
      "subject": 17,
      "condition": "Arithmetic",
      "trial": 1,
      "file": "Arithmetic_sub_17_trial1"
    },
    {
      "subject": 24,
      "condition": "Relax",
      "trial": 2,
      "file": "Relax_sub_24_trial2"
    },
    {
      "subject": 13,
      "condition": "Relax",
      "trial": 3,
      "file": "Relax_sub_13_trial3"
    },
    {
      "subject": 25,
      "condition": "Arithmetic",
      "trial": 2,
      "file": "Arithmetic_sub_25_trial2"
    },
    {
      "subject": 1,
      "condition": "Relax",
      "trial": 2,
      "file": "Relax_sub_1_trial2"
    },
    {
      "subject": 10,
      "condition": "Relax",
      "trial": 2,
      "file": "Relax_sub_10_trial2"
    },
    {
      "subject": 12,
      "condition": "Arithmetic",
      "trial": 1,
      "file": "Arithmetic_sub_12_trial1"
    },
    {
      "subject": 14,
      "condition": "Arithmetic",
      "trial": 3,
      "file": "Arithmetic_sub_14_trial3"
    },
    {
      "subject": 11,
      "condition": "Relax",
      "trial": 3,
      "file": "Relax_sub_11_trial3"
    },
    {
      "subject": 16,
      "condition": "Arithmetic",
      "trial": 3,
      "file": "Arithmetic_sub_16_trial3"
    },
    {
      "subject": 14,
      "condition": "Relax",
      "trial": 2,
      "file": "Relax_sub_14_trial2"
    },
    {
      "subject": 11,
      "condition": "Arithmetic",
      "trial": 3,
      "file": "Arithmetic_sub_11_trial3"
    },
    {
      "subject": 16,
      "condition": "Relax",
      "trial": 3,
      "file": "Relax_sub_16_trial3"
    },
    {
      "subject": 22,
      "condition": "Arithmetic",
      "trial": 3,
      "file": "Arithmetic_sub_22_trial3"
    },
    {
      "subject": 21,
      "condition": "Arithmetic",
      "trial": 1,
      "file": "Arithmetic_sub_21_trial1"
    },
    {
      "subject": 13,
      "condition": "Relax",
      "trial": 1,
      "file": "Relax_sub_13_trial1"
    },
    {
      "subject": 22,
      "condition": "Relax",
      "trial": 2,
      "file": "Relax_sub_22_trial2"
    },
    {
      "subject": 22,
      "condition": "Arithmetic",
      "trial": 2,
      "file": "Arithmetic_sub_22_trial2"
    },
    {
      "subject": 14,
      "condition": "Relax",
      "trial": 1,
      "file": "Relax_sub_14_trial1"
    },
    {
      "subject": 15,
      "condition": "Arithmetic",
      "trial": 1,
      "file": "Arithmetic_sub_15_trial1"
    },
    {
      "subject": 20,
      "condition": "Relax",
      "trial": 2,
      "file": "Relax_sub_20_trial2"
    },
    {
      "subject": 14,
      "condition": "Arithmetic",
      "trial": 2,
      "file": "Arithmetic_sub_14_trial2"
    },
    {
      "subject": 10,
      "condition": "Arithmetic",
      "trial": 2,
      "file": "Arithmetic_sub_10_trial2"
    },
    {
      "subject": 12,
      "condition": "Relax",
      "trial": 2,
      "file": "Relax_sub_12_trial2"
    },
    {
      "subject": 1,
      "condition": "Arithmetic",
      "trial": 1,
      "file": "Arithmetic_sub_1_trial1"
    },
    {
      "subject": 10,
      "condition": "Arithmetic",
      "trial": 3,
      "file": "Arithmetic_sub_10_trial3"
    },
    {
      "subject": 16,
      "condition": "Relax",
      "trial": 1,
      "file": "Relax_sub_16_trial1"
    },
    {
      "subject": 21,
      "condition": "Relax",
      "trial": 2,
      "file": "Relax_sub_21_trial2"
    },
    {
      "subject": 23,
      "condition": "Relax",
      "trial": 1,
      "file": "Relax_sub_23_trial1"
    },
    {
      "subject": 15,
      "condition": "Relax",
      "trial": 2,
      "file": "Relax_sub_15_trial2"
    },
    {
      "subject": 10,
      "condition": "Relax",
      "trial": 3,
      "file": "Relax_sub_10_trial3"
    },
    {
      "subject": 15,
      "condition": "Arithmetic",
      "trial": 3,
      "file": "Arithmetic_sub_15_trial3"
    },
    {
      "subject": 11,
      "condition": "Relax",
      "trial": 2,
      "file": "Relax_sub_11_trial2"
    },
    {
      "subject": 20,
      "condition": "Relax",
      "trial": 3,
      "file": "Relax_sub_20_trial3"
    },
    {
      "subject": 15,
      "condition": "Relax",
      "trial": 3,
      "file": "Relax_sub_15_trial3"
    },
    {
      "subject": 20,
      "condition": "Arithmetic",
      "trial": 1,
      "file": "Arithmetic_sub_20_trial1"
    },
    {
      "subject": 11,
      "condition": "Relax",
      "trial": 1,
      "file": "Relax_sub_11_trial1"
    },
    {
      "subject": 10,
      "condition": "Arithmetic",
      "trial": 1,
      "file": "Arithmetic_sub_10_trial1"
    },
    {
      "subject": 17,
      "condition": "Arithmetic",
      "trial": 3,
      "file": "Arithmetic_sub_17_trial3"
    },
    {
      "subject": 12,
      "condition": "Relax",
      "trial": 1,
      "file": "Relax_sub_12_trial1"
    },
    {
      "subject": 11,
      "condition": "Arithmetic",
      "trial": 2,
      "file": "Arithmetic_sub_11_trial2"
    },
    {
      "subject": 14,
      "condition": "Relax",
      "trial": 3,
      "file": "Relax_sub_14_trial3"
    },
    {
      "subject": 1,
      "condition": "Relax",
      "trial": 1,
      "file": "Relax_sub_1_trial1"
    },
    {
      "subject": 18,
      "condition": "Arithmetic",
      "trial": 3,
      "file": "Arithmetic_sub_18_trial3"
    },
    {
      "subject": 23,
      "condition": "Relax",
      "trial": 3,
      "file": "Relax_sub_23_trial3"
    },
    {
      "subject": 12,
      "condition": "Arithmetic",
      "trial": 3,
      "file": "Arithmetic_sub_12_trial3"
    },
    {
      "subject": 18,
      "condition": "Arithmetic",
      "trial": 1,
      "file": "Arithmetic_sub_18_trial1"
    }
  ]
}